daprot
