Metadata-Version: 1.0
Name: daprot
Version: 1.1.0
Summary: daprot is a data prototyper and mapper library.
Home-page: UNKNOWN
Author: Bence Faludi
Author-email: bence@ozmo.hu
License: GPL
Platform: UNKNOWN
